martin_eden/__init__.py
martin_eden/base.py
martin_eden/core.py
martin_eden/database.py
martin_eden/example.json
martin_eden/http_utils.py
martin_eden/logs.py
martin_eden/openapi.py
martin_eden/routing.py
martin_eden/settings.py
martin_eden/swg.html
martin_eden/utils.py
martin_eden-0.11.1.dist-info/METADATA
martin_eden-0.11.1.dist-info/WHEEL
martin_eden-0.11.1.dist-info/RECORD
