Metadata-Version: 2.1
Name: martin-eden
Version: 0.11.1
Summary: async backend framework on sockets
Home-page: https://github.com/mrtedn21/Eden
Author: mrtedn21
Author-email: bezgin.sasha06@gmail.com
Requires-Python: >=3.11,<4.0
Classifier: Programming Language :: Python :: 3
Classifier: Programming Language :: Python :: 3.11
Classifier: Programming Language :: Python :: 3.12
Requires-Dist: alembic (>=1.12.1,<2.0.0)
Requires-Dist: asyncpg (>=0.29.0,<0.30.0)
Requires-Dist: dacite (>=1.8.1,<2.0.0)
Requires-Dist: marshmallow (>=3.20.1,<4.0.0)
Requires-Dist: marshmallow-enum (>=1.5.1,<2.0.0)
Requires-Dist: marshmallow-jsonschema (>=0.13.0,<0.14.0)
Requires-Dist: psycopg2 (>=2.9.9,<3.0.0)
Requires-Dist: sqlalchemy (>=2.0.23,<3.0.0)
Requires-Dist: uvloop (>=0.19.0,<0.20.0)
Project-URL: Repository, https://github.com/mrtedn21/Eden
